westData/__init__.py
westData/modelTools.py
westData/riskControl.py
westData-1.1.0.dist-info/LICENSE.txt
westData-1.1.0.dist-info/METADATA
westData-1.1.0.dist-info/WHEEL
westData-1.1.0.dist-info/top_level.txt
westData-1.1.0.dist-info/RECORD
