Metadata-Version: 2.1
Name: westData
Version: 1.1.0
Summary: A small example package
Author: Alexander
Author-email: Alexander <alexander@yuctime.com>
Classifier: Programming Language :: Python :: 3
Classifier: License :: OSI Approved :: MIT License
Classifier: Operating System :: OS Independent
Requires-Python: >=3.6
License-File: LICENSE.txt
Requires-Dist: sklearn
Requires-Dist: lightgbm
Requires-Dist: xgboost
Requires-Dist: numpy
Requires-Dist: pandas
Requires-Dist: joblib
Requires-Dist: toad
